MANIFEST.in
README.md
nose.cfg
requirements.txt
setup.py
python_grpc_prometheus/__init__.py
python_grpc_prometheus/client_metrics.py
python_grpc_prometheus/prometheus_client_interceptor.py
python_grpc_prometheus/prometheus_server_interceptor.py
python_grpc_prometheus/server_metrics.py
python_grpc_prometheus/util.py
python_grpc_prometheus.egg-info/PKG-INFO
python_grpc_prometheus.egg-info/SOURCES.txt
python_grpc_prometheus.egg-info/dependency_links.txt
python_grpc_prometheus.egg-info/requires.txt
python_grpc_prometheus.egg-info/top_level.txt