Metadata-Version: 2.1
Name: python-grpc-prometheus
Version: 0.2.0
Summary: Python gRPC Prometheus Interceptors
Home-page: https://github.com/zhyon404/python-grpc-prometheus
Author: Zhang Yong
Author-email: yongzhang1@foxmail.com
License: MIT
Platform: UNKNOWN
